{
  "swimmers": [
    {
      "firstName": "Jason",
      "lastName": "Allen",
      "dateOfBirth": "2009-09-02",
      "gender": "Male",
      "asaNo": "1381735"
    },
    {
      "firstName": "Rudy",
      "lastName": "Aspland",
      "dateOfBirth": "2015-05-05",
      "gender": "Male",
      "asaNo": "1714439"
    },
    {
      "firstName": "Sophie",
      "lastName": "Attwood",
      "dateOfBirth": "2015-09-12",
      "gender": "Female",
      "asaNo": "1752243"
    },
    {
      "firstName": "Yaman",
      "lastName": "Ayral",
      "dateOfBirth": "2014-08-06",
      "gender": "Male",
      "asaNo": "1807130"
    },
    {
      "firstName": "Ava",
      "lastName": "Baker",
      "dateOfBirth": "2015-04-23",
      "gender": "Female",
      "asaNo": "1761987"
    },
    {
      "firstName": "William",
      "lastName": "Bass",
      "dateOfBirth": "2013-07-31",
      "gender": "Male",
      "asaNo": "1781488"
    },
    {
      "firstName": "Thomas",
      "lastName": "Bass",
      "dateOfBirth": "2015-05-11",
      "gender": "Male",
      "asaNo": "1816801"
    },
    {
      "firstName": "Olivia",
      "lastName": "Bayley",
      "dateOfBirth": "2009-12-20",
      "gender": "Female",
      "asaNo": "1576284"
    },
    {
      "firstName": "Clive",
      "lastName": "Benson",
      "dateOfBirth": "1963-09-23",
      "gender": "Male",
      "asaNo": "412216"
    },
    {
      "firstName": "Richard",
      "lastName": "Brinck",
      "dateOfBirth": "1966-10-08",
      "gender": "Male",
      "asaNo": "81368"
    },
    {
      "firstName": "Lachlan",
      "lastName": "Brown",
      "dateOfBirth": "2015-01-24",
      "gender": "Male",
      "asaNo": "1722681"
    },
    {
      "firstName": "Rebecca",
      "lastName": "Brown",
      "dateOfBirth": "2017-04-19",
      "gender": "Female",
      "asaNo": "1807118"
    },
    {
      "firstName": "Mason",
      "lastName": "Browne",
      "dateOfBirth": "2014-03-15",
      "gender": "Male",
      "asaNo": "1820865"
    },
    {
      "firstName": "Anthony",
      "lastName": "Browne",
      "dateOfBirth": "1977-07-07",
      "gender": "Male",
      "asaNo": "476587"
    },
    {
      "firstName": "Patrick",
      "lastName": "Campbell",
      "dateOfBirth": "2015-09-26",
      "gender": "Male",
      "asaNo": "1786055"
    },
    {
      "firstName": "Willow",
      "lastName": "Casson",
      "dateOfBirth": "2017-07-20",
      "gender": "Female",
      "asaNo": "1795735"
    },
    {
      "firstName": "Lilly",
      "lastName": "Casson",
      "dateOfBirth": "2013-09-22",
      "gender": "Female",
      "asaNo": "1695954"
    },
    {
      "firstName": "Owen",
      "lastName": "Channing",
      "dateOfBirth": "2010-02-03",
      "gender": "Male",
      "asaNo": "1495546"
    },
    {
      "firstName": "Joshua",
      "lastName": "Chapman",
      "dateOfBirth": "2014-04-14",
      "gender": "Male",
      "asaNo": "1807129"
    },
    {
      "firstName": "Lara",
      "lastName": "Charlton",
      "dateOfBirth": "1998-09-28",
      "gender": "Female",
      "asaNo": "513043"
    },
    {
      "firstName": "James",
      "lastName": "Clark",
      "dateOfBirth": "2011-03-04",
      "gender": "Male",
      "asaNo": "1490686"
    },
    {
      "firstName": "Antony",
      "lastName": "Clark",
      "dateOfBirth": "1981-03-24",
      "gender": "Male",
      "asaNo": "647731"
    },
    {
      "firstName": "Tom",
      "lastName": "Clarke",
      "dateOfBirth": "2011-07-17",
      "gender": "Male",
      "asaNo": "1708709"
    },
    {
      "firstName": "James",
      "lastName": "Clarkson",
      "dateOfBirth": "2008-05-29",
      "gender": "Male",
      "asaNo": "1816781"
    },
    {
      "firstName": "Ava",
      "lastName": "Clegg",
      "dateOfBirth": "2015-08-11",
      "gender": "Female",
      "asaNo": "1828385"
    },
    {
      "firstName": "Kiana",
      "lastName": "Coley",
      "dateOfBirth": "2013-09-28",
      "gender": "Female",
      "asaNo": "1638262"
    },
    {
      "firstName": "Miya",
      "lastName": "Cook",
      "dateOfBirth": "2014-02-09",
      "gender": "Female",
      "asaNo": "1714438"
    },
    {
      "firstName": "Tilly",
      "lastName": "Cooper",
      "dateOfBirth": "2013-07-07",
      "gender": "Female",
      "asaNo": "1786042"
    },
    {
      "firstName": "Darcy",
      "lastName": "Cooper",
      "dateOfBirth": "2014-09-12",
      "gender": "Male",
      "asaNo": "1807119"
    },
    {
      "firstName": "Emilia",
      "lastName": "Date",
      "dateOfBirth": "2012-10-22",
      "gender": "Female",
      "asaNo": "1669813"
    },
    {
      "firstName": "Barnaby",
      "lastName": "Day",
      "dateOfBirth": "2013-08-28",
      "gender": "Male",
      "asaNo": "1765952"
    },
    {
      "firstName": "Eva",
      "lastName": "Dickinson",
      "dateOfBirth": "2010-01-14",
      "gender": "Female",
      "asaNo": "1576280"
    },
    {
      "firstName": "William",
      "lastName": "Dimmack",
      "dateOfBirth": "2014-02-10",
      "gender": "Male",
      "asaNo": "1781490"
    },
    {
      "firstName": "Cara",
      "lastName": "Durieu",
      "dateOfBirth": "2016-06-28",
      "gender": "Female",
      "asaNo": "1828381"
    },
    {
      "firstName": "Alexander",
      "lastName": "Dzavan",
      "dateOfBirth": "2012-10-23",
      "gender": "Male",
      "asaNo": "1638239"
    },
    {
      "firstName": "Ted",
      "lastName": "Eales",
      "dateOfBirth": "2010-11-15",
      "gender": "Male",
      "asaNo": "1443419"
    },
    {
      "firstName": "Jack",
      "lastName": "Einchcomb",
      "dateOfBirth": "2016-06-01",
      "gender": "Male",
      "asaNo": "1773590"
    },
    {
      "firstName": "George",
      "lastName": "Esch",
      "dateOfBirth": "2012-11-21",
      "gender": "Male",
      "asaNo": "1703480"
    },
    {
      "firstName": "Edward",
      "lastName": "Evans",
      "dateOfBirth": "2011-08-12",
      "gender": "Male",
      "asaNo": "1796311"
    },
    {
      "firstName": "Naomi",
      "lastName": "Everard",
      "dateOfBirth": "2016-02-23",
      "gender": "Female",
      "asaNo": "1781481"
    },
    {
      "firstName": "Harry",
      "lastName": "Fagan",
      "dateOfBirth": "2008-02-22",
      "gender": "Male",
      "asaNo": "1333751"
    },
    {
      "firstName": "Bella",
      "lastName": "Falconi",
      "dateOfBirth": "2012-01-20",
      "gender": "Female",
      "asaNo": "1786045"
    },
    {
      "firstName": "Benjamin",
      "lastName": "Falconi",
      "dateOfBirth": "2014-04-12",
      "gender": "Male",
      "asaNo": "1786043"
    },
    {
      "firstName": "Vincent",
      "lastName": "Fanning",
      "dateOfBirth": "1970-01-24",
      "gender": "Male",
      "asaNo": "1154425"
    },
    {
      "firstName": "Maya",
      "lastName": "Farmer",
      "dateOfBirth": "2004-09-03",
      "gender": "Female",
      "asaNo": "950074"
    },
    {
      "firstName": "Chris",
      "lastName": "Fawkes",
      "dateOfBirth": "1977-11-01",
      "gender": "Male",
      "asaNo": "3354"
    },
    {
      "firstName": "Nicholas",
      "lastName": "Fradgley",
      "dateOfBirth": "2008-04-14",
      "gender": "Male",
      "asaNo": "1795732"
    },
    {
      "firstName": "Jayden",
      "lastName": "Fu",
      "dateOfBirth": "2014-09-16",
      "gender": "Male",
      "asaNo": "1757888"
    },
    {
      "firstName": "Alexander",
      "lastName": "Gaw",
      "dateOfBirth": "2012-02-15",
      "gender": "Male",
      "asaNo": "1820869"
    },
    {
      "firstName": "Igor",
      "lastName": "Gladysz",
      "dateOfBirth": "2012-06-21",
      "gender": "Male",
      "asaNo": "1807128"
    },
    {
      "firstName": "Emma",
      "lastName": "Goddard",
      "dateOfBirth": "2015-01-13",
      "gender": "Female",
      "asaNo": "1669821"
    },
    {
      "firstName": "Edward",
      "lastName": "Goddard",
      "dateOfBirth": "2010-07-17",
      "gender": "Male",
      "asaNo": "1423544"
    },
    {
      "firstName": "Oliver",
      "lastName": "Goddard",
      "dateOfBirth": "2008-11-18",
      "gender": "Male",
      "asaNo": "1398527"
    },
    {
      "firstName": "Brodie",
      "lastName": "Golabek",
      "dateOfBirth": "2016-02-07",
      "gender": "Male",
      "asaNo": "1795733"
    },
    {
      "firstName": "Alexander",
      "lastName": "Gordon",
      "dateOfBirth": "2009-12-11",
      "gender": "Male",
      "asaNo": "1495547"
    },
    {
      "firstName": "Christopher",
      "lastName": "Guilherme",
      "dateOfBirth": "2015-02-06",
      "gender": "Male",
      "asaNo": "1461638"
    },
    {
      "firstName": "Kristian",
      "lastName": "Gulcz",
      "dateOfBirth": "2014-01-09",
      "gender": "Male",
      "asaNo": "1731315"
    },
    {
      "firstName": "Dylan",
      "lastName": "Hancock",
      "dateOfBirth": "2015-05-06",
      "gender": "Male",
      "asaNo": "1823449"
    },
    {
      "firstName": "Ava",
      "lastName": "Harper",
      "dateOfBirth": "2013-09-16",
      "gender": "Female",
      "asaNo": "1695966"
    },
    {
      "firstName": "Amy",
      "lastName": "Hart",
      "dateOfBirth": "2012-12-24",
      "gender": "Female",
      "asaNo": "1638242"
    },
    {
      "firstName": "Eva",
      "lastName": "Harvey",
      "dateOfBirth": "2013-08-07",
      "gender": "Female",
      "asaNo": "1761986"
    },
    {
      "firstName": "Annabelle",
      "lastName": "Hawes",
      "dateOfBirth": "2014-11-05",
      "gender": "Female",
      "asaNo": "1828383"
    },
    {
      "firstName": "Nell",
      "lastName": "Hayward",
      "dateOfBirth": "2015-07-11",
      "gender": "Female",
      "asaNo": "1731313"
    },
    {
      "firstName": "Zach",
      "lastName": "Hayward",
      "dateOfBirth": "2010-03-20",
      "gender": "Male",
      "asaNo": "1515138"
    },
    {
      "firstName": "Ella",
      "lastName": "Head",
      "dateOfBirth": "2010-09-13",
      "gender": "Female",
      "asaNo": "1402948"
    },
    {
      "firstName": "Dexter",
      "lastName": "Herbert",
      "dateOfBirth": "2012-12-03",
      "gender": "Male",
      "asaNo": "1669819"
    },
    {
      "firstName": "Chloe",
      "lastName": "Hodgson",
      "dateOfBirth": "2008-09-30",
      "gender": "Female",
      "asaNo": "1268202"
    },
    {
      "firstName": "Jude",
      "lastName": "Hookings",
      "dateOfBirth": "2016-06-08",
      "gender": "Male",
      "asaNo": "1816775"
    },
    {
      "firstName": "Rowan",
      "lastName": "Hookings",
      "dateOfBirth": "2014-06-19",
      "gender": "Male",
      "asaNo": "1816792"
    },
    {
      "firstName": "Olivia",
      "lastName": "Hooper",
      "dateOfBirth": "2013-05-21",
      "gender": "Female",
      "asaNo": "1367407"
    },
    {
      "firstName": "Hannah",
      "lastName": "Hooper",
      "dateOfBirth": "2007-03-09",
      "gender": "Female",
      "asaNo": "1303479"
    },
    {
      "firstName": "Sara",
      "lastName": "Hunter",
      "dateOfBirth": "2017-08-06",
      "gender": "Female",
      "asaNo": "1807115"
    },
    {
      "firstName": "Evan",
      "lastName": "Ian",
      "dateOfBirth": "2012-01-19",
      "gender": "Male",
      "asaNo": "1731314"
    },
    {
      "firstName": "Francesca",
      "lastName": "Irani",
      "dateOfBirth": "2009-12-06",
      "gender": "Female",
      "asaNo": "1418032"
    },
    {
      "firstName": "Lily",
      "lastName": "Jacobs",
      "dateOfBirth": "2014-10-20",
      "gender": "Female",
      "asaNo": "1820871"
    },
    {
      "firstName": "Beth",
      "lastName": "Johnston",
      "dateOfBirth": "2016-04-27",
      "gender": "Female",
      "asaNo": "1828384"
    },
    {
      "firstName": "Amy",
      "lastName": "Jones",
      "dateOfBirth": "2009-07-25",
      "gender": "Female",
      "asaNo": "1379202"
    },
    {
      "firstName": "Emma",
      "lastName": "Jones",
      "dateOfBirth": "2005-01-19",
      "gender": "Female",
      "asaNo": "1250355"
    },
    {
      "firstName": "Paul",
      "lastName": "Jones",
      "dateOfBirth": "1974-07-01",
      "gender": "Male",
      "asaNo": "1308501"
    },
    {
      "firstName": "Jasmine",
      "lastName": "Key",
      "dateOfBirth": "2011-08-16",
      "gender": "Female",
      "asaNo": "1330564"
    },
    {
      "firstName": "Ho",
      "lastName": "Kiu Kan",
      "dateOfBirth": "2011-04-02",
      "gender": "Male",
      "asaNo": "1781492"
    },
    {
      "firstName": "Chelsea",
      "lastName": "Knight",
      "dateOfBirth": "1985-02-01",
      "gender": "Female",
      "asaNo": "1795736"
    },
    {
      "firstName": "Lauren",
      "lastName": "Knight",
      "dateOfBirth": "2014-01-17",
      "gender": "Female",
      "asaNo": "1825972"
    },
    {
      "firstName": "Riley",
      "lastName": "Knuszka",
      "dateOfBirth": "2013-06-21",
      "gender": "Male",
      "asaNo": "1826366"
    },
    {
      "firstName": "Dominika",
      "lastName": "Kolelis",
      "dateOfBirth": "2011-07-29",
      "gender": "Female",
      "asaNo": "1816808"
    },
    {
      "firstName": "Ellie",
      "lastName": "Kong",
      "dateOfBirth": "2013-01-18",
      "gender": "Female",
      "asaNo": "1638259"
    },
    {
      "firstName": "Michelle",
      "lastName": "Laverick",
      "dateOfBirth": "1973-06-09",
      "gender": "Female",
      "asaNo": "1311629"
    },
    {
      "firstName": "Sam",
      "lastName": "Law Chin Yung",
      "dateOfBirth": "2004-11-09",
      "gender": "Male",
      "asaNo": "1130117"
    },
    {
      "firstName": "Harry",
      "lastName": "Laws",
      "dateOfBirth": "2015-12-04",
      "gender": "Male",
      "asaNo": "1795734"
    },
    {
      "firstName": "Evan",
      "lastName": "Lee",
      "dateOfBirth": "2014-01-17",
      "gender": "Male",
      "asaNo": "1781489"
    },
    {
      "firstName": "James",
      "lastName": "Leung",
      "dateOfBirth": "2016-07-12",
      "gender": "Male",
      "asaNo": "1797946"
    },
    {
      "firstName": "Kaylem",
      "lastName": "Livesey",
      "dateOfBirth": "2012-04-18",
      "gender": "Male",
      "asaNo": "1576287"
    },
    {
      "firstName": "Kylie-Rae",
      "lastName": "Livesey",
      "dateOfBirth": "2013-11-06",
      "gender": "Female",
      "asaNo": "1605730"
    },
    {
      "firstName": "Audrey",
      "lastName": "Lofts",
      "dateOfBirth": "2015-06-22",
      "gender": "Female",
      "asaNo": "1820863"
    },
    {
      "firstName": "Halle",
      "lastName": "Love",
      "dateOfBirth": "2012-03-08",
      "gender": "Female",
      "asaNo": "1807120"
    },
    {
      "firstName": "Toby",
      "lastName": "Love",
      "dateOfBirth": "2016-07-04",
      "gender": "Male",
      "asaNo": "1786048"
    },
    {
      "firstName": "Ollie",
      "lastName": "Lovick",
      "dateOfBirth": "2009-01-17",
      "gender": "Male",
      "asaNo": "1515134"
    },
    {
      "firstName": "Rupert",
      "lastName": "Mack",
      "dateOfBirth": "2014-12-15",
      "gender": "Male",
      "asaNo": "1820223"
    },
    {
      "firstName": "Elliot",
      "lastName": "Mack",
      "dateOfBirth": "2012-08-27",
      "gender": "Male",
      "asaNo": "1706528"
    },
    {
      "firstName": "Tabitha",
      "lastName": "Meadows",
      "dateOfBirth": "2014-06-16",
      "gender": "Female",
      "asaNo": "1781487"
    },
    {
      "firstName": "Luke",
      "lastName": "Meeks",
      "dateOfBirth": "2008-04-08",
      "gender": "Male",
      "asaNo": "1386221"
    },
    {
      "firstName": "Oliver",
      "lastName": "Mellor",
      "dateOfBirth": "2006-02-08",
      "gender": "Male",
      "asaNo": "866400"
    },
    {
      "firstName": "Andrea",
      "lastName": "Merritt",
      "dateOfBirth": "1966-04-09",
      "gender": "Female",
      "asaNo": "25036"
    },
    {
      "firstName": "Ariya",
      "lastName": "Mirhosseini",
      "dateOfBirth": "2010-01-24",
      "gender": "Male",
      "asaNo": "1638244"
    },
    {
      "firstName": "Anita",
      "lastName": "Mirhosseini",
      "dateOfBirth": "2012-12-16",
      "gender": "Female",
      "asaNo": "1757894"
    },
    {
      "firstName": "Joshua",
      "lastName": "Montgomery",
      "dateOfBirth": "1998-01-10",
      "gender": "Male",
      "asaNo": "316522"
    },
    {
      "firstName": "John",
      "lastName": "Morton",
      "dateOfBirth": "2014-02-01",
      "gender": "Male",
      "asaNo": "1365942"
    },
    {
      "firstName": "Vivienne",
      "lastName": "Morton",
      "dateOfBirth": "2011-10-25",
      "gender": "Female",
      "asaNo": "1365943"
    },
    {
      "firstName": "Tvisha",
      "lastName": "Nair",
      "dateOfBirth": "2014-03-16",
      "gender": "Female",
      "asaNo": "1731316"
    },
    {
      "firstName": "Cheuk",
      "lastName": "Nam Kan",
      "dateOfBirth": "2017-02-07",
      "gender": "Female",
      "asaNo": "1814120"
    },
    {
      "firstName": "Isobel",
      "lastName": "Neighbour",
      "dateOfBirth": "2005-10-01",
      "gender": "Female",
      "asaNo": "1327231"
    },
    {
      "firstName": "Lily",
      "lastName": "Neighbour",
      "dateOfBirth": "2010-05-06",
      "gender": "Female",
      "asaNo": "1423543"
    },
    {
      "firstName": "Iulia",
      "lastName": "Nestor",
      "dateOfBirth": "2010-08-30",
      "gender": "Female",
      "asaNo": "1657393"
    },
    {
      "firstName": "Molly",
      "lastName": "Nicholls",
      "dateOfBirth": "2015-11-09",
      "gender": "Female",
      "asaNo": "1786050"
    },
    {
      "firstName": "Ben",
      "lastName": "Orme",
      "dateOfBirth": "2010-10-13",
      "gender": "Male",
      "asaNo": "1471458"
    },
    {
      "firstName": "Sam",
      "lastName": "Orme",
      "dateOfBirth": "2016-05-07",
      "gender": "Male",
      "asaNo": "1786052"
    },
    {
      "firstName": "Josh",
      "lastName": "Orme",
      "dateOfBirth": "2013-02-05",
      "gender": "Male",
      "asaNo": "1605743"
    },
    {
      "firstName": "Florence",
      "lastName": "Ostler",
      "dateOfBirth": "2017-07-28",
      "gender": "Female",
      "asaNo": "1794962"
    },
    {
      "firstName": "Charlotte",
      "lastName": "Pallangyo",
      "dateOfBirth": "1990-07-12",
      "gender": "Female",
      "asaNo": "1638256"
    },
    {
      "firstName": "Riya",
      "lastName": "Pamma",
      "dateOfBirth": "2014-10-21",
      "gender": "Female",
      "asaNo": "1695969"
    },
    {
      "firstName": "Eleni",
      "lastName": "Pamma",
      "dateOfBirth": "2017-06-01",
      "gender": "Female",
      "asaNo": "1807116"
    },
    {
      "firstName": "Amara",
      "lastName": "Pamma",
      "dateOfBirth": "2017-06-01",
      "gender": "Female",
      "asaNo": "1797934"
    },
    {
      "firstName": "Abhay",
      "lastName": "Paruchuri",
      "dateOfBirth": "2010-06-25",
      "gender": "Male",
      "asaNo": "1584019"
    },
    {
      "firstName": "Emily",
      "lastName": "Paull",
      "dateOfBirth": "2010-12-17",
      "gender": "Female",
      "asaNo": "1502756"
    },
    {
      "firstName": "Jacob",
      "lastName": "Pavel",
      "dateOfBirth": "2014-06-14",
      "gender": "Male",
      "asaNo": "1757893"
    },
    {
      "firstName": "Joseph",
      "lastName": "Payne",
      "dateOfBirth": "2005-05-04",
      "gender": "Male",
      "asaNo": "1280212"
    },
    {
      "firstName": "James",
      "lastName": "Payne",
      "dateOfBirth": "2010-08-02",
      "gender": "Male",
      "asaNo": "1706530"
    },
    {
      "firstName": "Helen",
      "lastName": "Payne",
      "dateOfBirth": "1975-07-05",
      "gender": "Female",
      "asaNo": "1576282"
    },
    {
      "firstName": "Andrea",
      "lastName": "Peralta Salvador",
      "dateOfBirth": "2010-08-31",
      "gender": "Female",
      "asaNo": "1517826"
    },
    {
      "firstName": "Matthew",
      "lastName": "Perry",
      "dateOfBirth": "1976-07-13",
      "gender": "Male",
      "asaNo": "20643"
    },
    {
      "firstName": "Gyorgy",
      "lastName": "Posta",
      "dateOfBirth": "2008-04-14",
      "gender": "Male",
      "asaNo": "1357120"
    },
    {
      "firstName": "William",
      "lastName": "Powell",
      "dateOfBirth": "2013-06-25",
      "gender": "Male",
      "asaNo": "1816785"
    },
    {
      "firstName": "Thomas",
      "lastName": "Pride",
      "dateOfBirth": "2012-03-12",
      "gender": "Male",
      "asaNo": "1752228"
    },
    {
      "firstName": "Aashman",
      "lastName": "Rai",
      "dateOfBirth": "2012-09-15",
      "gender": "Male",
      "asaNo": "1826063"
    },
    {
      "firstName": "Malcolm",
      "lastName": "Rainier",
      "dateOfBirth": "1967-04-23",
      "gender": "Male",
      "asaNo": "38258"
    },
    {
      "firstName": "Daniel",
      "lastName": "Richards",
      "dateOfBirth": "1995-03-14",
      "gender": "Male",
      "asaNo": "387108"
    },
    {
      "firstName": "Lily",
      "lastName": "Riches",
      "dateOfBirth": "2011-10-20",
      "gender": "Female",
      "asaNo": "1483263"
    },
    {
      "firstName": "Isabelle",
      "lastName": "Riches",
      "dateOfBirth": "2013-07-02",
      "gender": "Female",
      "asaNo": "1579681"
    },
    {
      "firstName": "Luca",
      "lastName": "Righetti Zullo",
      "dateOfBirth": "2011-11-16",
      "gender": "Male",
      "asaNo": "1786064"
    },
    {
      "firstName": "Ellie",
      "lastName": "Robson-Rowan",
      "dateOfBirth": "2012-02-27",
      "gender": "Female",
      "asaNo": "1669811"
    },
    {
      "firstName": "Molly",
      "lastName": "Robson-Rowan",
      "dateOfBirth": "2016-01-30",
      "gender": "Female",
      "asaNo": "1708708"
    },
    {
      "firstName": "Rachael",
      "lastName": "Rock",
      "dateOfBirth": "1973-12-05",
      "gender": "Female",
      "asaNo": "60149"
    },
    {
      "firstName": "Zoe",
      "lastName": "Sadler",
      "dateOfBirth": "1973-10-30",
      "gender": "Female",
      "asaNo": "753455"
    },
    {
      "firstName": "Elizabeth",
      "lastName": "Sampson",
      "dateOfBirth": "2015-04-23",
      "gender": "Female",
      "asaNo": "1757890"
    },
    {
      "firstName": "Edward",
      "lastName": "Sampson",
      "dateOfBirth": "2017-02-16",
      "gender": "Male",
      "asaNo": "1820867"
    },
    {
      "firstName": "Laetizia",
      "lastName": "Sandoval",
      "dateOfBirth": "2012-02-03",
      "gender": "Female",
      "asaNo": "1765955"
    },
    {
      "firstName": "Arrice",
      "lastName": "Scott",
      "dateOfBirth": "2013-07-30",
      "gender": "Female",
      "asaNo": "1797937"
    },
    {
      "firstName": "Gideon",
      "lastName": "Smith",
      "dateOfBirth": "2008-07-05",
      "gender": "Male",
      "asaNo": "1311972"
    },
    {
      "firstName": "Cerys",
      "lastName": "Snelling",
      "dateOfBirth": "2009-09-09",
      "gender": "Female",
      "asaNo": "1346759"
    },
    {
      "firstName": "Miles",
      "lastName": "Spillane",
      "dateOfBirth": "2017-05-12",
      "gender": "Male",
      "asaNo": "1814119"
    },
    {
      "firstName": "George",
      "lastName": "Stanchev",
      "dateOfBirth": "2012-03-27",
      "gender": "Male",
      "asaNo": "1669822"
    },
    {
      "firstName": "Eva",
      "lastName": "Stancheva",
      "dateOfBirth": "2010-05-08",
      "gender": "Female",
      "asaNo": "1494875"
    },
    {
      "firstName": "Iwan",
      "lastName": "Stone",
      "dateOfBirth": "2013-03-23",
      "gender": "Male",
      "asaNo": "1706531"
    },
    {
      "firstName": "Finlay",
      "lastName": "Stuart",
      "dateOfBirth": "2010-05-07",
      "gender": "Male",
      "asaNo": "1440193"
    },
    {
      "firstName": "Arnav",
      "lastName": "Swarup",
      "dateOfBirth": "2012-09-20",
      "gender": "Male",
      "asaNo": "1669806"
    },
    {
      "firstName": "Katie",
      "lastName": "Taylor",
      "dateOfBirth": "2010-12-08",
      "gender": "Female",
      "asaNo": "1638228"
    },
    {
      "firstName": "Sarah",
      "lastName": "Taylor",
      "dateOfBirth": "1968-06-25",
      "gender": "Female",
      "asaNo": "1379575"
    },
    {
      "firstName": "Dave",
      "lastName": "Thomas",
      "dateOfBirth": "1956-11-17",
      "gender": "Male",
      "asaNo": "1714437"
    },
    {
      "firstName": "Ffion",
      "lastName": "Thomas",
      "dateOfBirth": "2000-03-09",
      "gender": "Female",
      "asaNo": "540268"
    },
    {
      "firstName": "Alice",
      "lastName": "Tillett",
      "dateOfBirth": "2011-08-23",
      "gender": "Female",
      "asaNo": "1638246"
    },
    {
      "firstName": "Iris",
      "lastName": "Tong",
      "dateOfBirth": "2015-03-04",
      "gender": "Female",
      "asaNo": "1695968"
    },
    {
      "firstName": "Balazs",
      "lastName": "Toth",
      "dateOfBirth": "2000-05-16",
      "gender": "Male",
      "asaNo": "916147"
    },
    {
      "firstName": "Emilia",
      "lastName": "Turner",
      "dateOfBirth": "2016-11-07",
      "gender": "Female",
      "asaNo": "1795737"
    },
    {
      "firstName": "Winnie",
      "lastName": "Uccelli",
      "dateOfBirth": "2015-07-16",
      "gender": "Female",
      "asaNo": "1797940"
    },
    {
      "firstName": "Abigail",
      "lastName": "van der Westhuizen",
      "dateOfBirth": "2012-06-07",
      "gender": "Female",
      "asaNo": "1695953"
    },
    {
      "firstName": "Paige",
      "lastName": "van der Westhuizen",
      "dateOfBirth": "2014-01-16",
      "gender": "Female",
      "asaNo": "1695965"
    },
    {
      "firstName": "Hannah",
      "lastName": "Vanstone",
      "dateOfBirth": "2010-08-23",
      "gender": "Female",
      "asaNo": "1430482"
    },
    {
      "firstName": "Henry",
      "lastName": "Wakefield",
      "dateOfBirth": "2014-07-22",
      "gender": "Male",
      "asaNo": "1797943"
    },
    {
      "firstName": "Christian",
      "lastName": "Walker",
      "dateOfBirth": "2013-09-14",
      "gender": "Male",
      "asaNo": "1733196"
    },
    {
      "firstName": "Millie",
      "lastName": "Wall",
      "dateOfBirth": "2013-06-06",
      "gender": "Female",
      "asaNo": "1820224"
    },
    {
      "firstName": "Sophia",
      "lastName": "Wallis",
      "dateOfBirth": "1997-09-20",
      "gender": "Female",
      "asaNo": "417274"
    },
    {
      "firstName": "Max",
      "lastName": "Walton",
      "dateOfBirth": "2006-04-22",
      "gender": "Male",
      "asaNo": "1229584"
    },
    {
      "firstName": "Tegan",
      "lastName": "Ward",
      "dateOfBirth": "2001-05-15",
      "gender": "Female",
      "asaNo": "757664"
    },
    {
      "firstName": "Sophie",
      "lastName": "Warne",
      "dateOfBirth": "2012-07-02",
      "gender": "Female",
      "asaNo": "1371455"
    },
    {
      "firstName": "Thomas",
      "lastName": "Warne",
      "dateOfBirth": "2010-01-21",
      "gender": "Male",
      "asaNo": "1382336"
    },
    {
      "firstName": "Dexter",
      "lastName": "Welch",
      "dateOfBirth": "2016-08-01",
      "gender": "Male",
      "asaNo": "1781486"
    },
    {
      "firstName": "Skylar",
      "lastName": "Welch",
      "dateOfBirth": "2014-10-31",
      "gender": "Female",
      "asaNo": "1669827"
    },
    {
      "firstName": "Ella",
      "lastName": "Worship",
      "dateOfBirth": "2008-03-19",
      "gender": "Female",
      "asaNo": "1502759"
    },
    {
      "firstName": "Samuel",
      "lastName": "Yates",
      "dateOfBirth": "2008-12-24",
      "gender": "Male",
      "asaNo": "1585300"
    }
  ]
}
